aioairtable/__init__.py
aioairtable/_version.py
aioairtable/aioairtable.py
aioairtable/helpers.py
aioairtable/py.typed
aioairtable-0.2.2.dist-info/WHEEL
aioairtable-0.2.2.dist-info/METADATA
aioairtable-0.2.2.dist-info/RECORD
