Metadata-Version: 2.3
Name: aioairtable
Version: 0.2.2
Summary: Asynchronous client library for Airtable API
Author: Gleb Chipiga
License: MIT License
Classifier: Intended Audience :: Developers
Classifier: Programming Language :: Python
Classifier: Programming Language :: Python :: 3
Classifier: Programming Language :: Python :: 3.11
Classifier: Programming Language :: Python :: 3.12
Classifier: Programming Language :: Python :: 3.13
Classifier: License :: OSI Approved :: MIT License
Classifier: Development Status :: 4 - Beta
Classifier: Operating System :: POSIX
Classifier: Operating System :: MacOS :: MacOS X
Classifier: Operating System :: Microsoft :: Windows
Classifier: Topic :: Internet
Classifier: Framework :: AsyncIO
Classifier: Topic :: Office/Business
Classifier: Topic :: Office/Business :: Financial :: Spreadsheet
Classifier: Topic :: Office/Business :: Groupware
Classifier: Topic :: Office/Business :: Scheduling
Requires-Dist: aiohttp
Requires-Dist: multidict
Requires-Dist: yarl
Requires-Dist: backoff>=2
Requires-Dist: aiofreqlimit>=0.0.7
Requires-Dist: msgspec
Requires-Dist: typing-extensions
Requires-Python: >=3.11, <3.14
Project-URL: Homepage, https://github.com/gleb-chipiga/aioairtable
